{"docs_components_alert.md":"C6L9_8iu","docs_components_avatar.md":"DY91YSGc","docs_components_badge.md":"BxvCQtTD","docs_components_breadcrumbs.md":"aSv8T19S","docs_components_button.md":"C_TT8VPw","docs_components_calendar.md":"DEnBsXeT","docs_components_charts.md":"B1uC6soY","docs_components_checkbox.md":"DtwpTk7w","docs_components_circularprogressbar.md":"BugYMWQk","docs_components_combobox.md":"BtOizfq6","docs_components_datepicker.md":"BxRrPXHQ","docs_components_dialog.md":"D4Z9IgPu","docs_components_divider.md":"Wpmlz4cb","docs_components_dropdown.md":"DuNmtV7D","docs_components_errormessage.md":"s34t_vKH","docs_components_fileuploader.md":"DU_aCGXa","docs_components_formcontrol.md":"1s_Ar1VY","docs_components_itemlistrow.md":"DZU--cy9","docs_components_keyboardshortcutsmodal.md":"YR4SkJHg","docs_components_legacy.md":"C_gGliDC","docs_components_listview.md":"BJKRMNcv","docs_components_monthpicker.md":"DubTPZwX","docs_components_multiselect.md":"C61m4GCf","docs_components_password.md":"iplS8s79","docs_components_popover.md":"7Ht-Sc8u","docs_components_progress.md":"DPJCeDhj","docs_components_rating.md":"BPYXhQ-7","docs_components_select.md":"Dj2I4cBD","docs_components_sidebar.md":"Ch5KI-aG","docs_components_slider.md":"CP0Jqyab","docs_components_switch.md":"DyqkTWzX","docs_components_tabs.md":"Crg25VL7","docs_components_textarea.md":"Uwg6cKbV","docs_components_texteditor.md":"CaIrf7fL","docs_components_textinput.md":"Drw5hxv4","docs_components_timepicker.md":"BKHTzXcq","docs_components_toast.md":"D73NqOwn","docs_components_tooltip.md":"Bg9pBoFW","docs_components_tree.md":"B7rclftD","docs_data-fetching_document-resource.md":"MP_yIEGA","docs_data-fetching_list-resource.md":"5XUcDaDt","docs_data-fetching_resource.md":"FaGoH_d2","docs_design-system_background-color.md":"CPpeqhA6","docs_design-system_border-color.md":"Be9mQ9Sn","docs_design-system_border-radius.md":"IuMqt9LH","docs_design-system_drop-shadow.md":"Cefqrq6Q","docs_design-system_text-color.md":"BE53LYDd","docs_design-system_text.md":"B2066nZs","docs_frappe_link.md":"DX7kX5GJ","docs_getting-started.md":"BNbsOMAk","docs_introduction.md":"CE5z1Ana","docs_migration.md":"YdByzyoY","docs_molecules_editor.md":"Clxdxr03","docs_other_directives.md":"BOKfNja2","docs_other_icons.md":"CLbHhppx","docs_other_utilities.md":"C-NBl6an","index.md":"DZ8h2HBp"}
