{"docs_components_alert.md":"OGcVECQj","docs_components_avatar.md":"B47Lmgqg","docs_components_badge.md":"Dmf1gg0n","docs_components_breadcrumbs.md":"bJjjlf3s","docs_components_button.md":"B5sKNBYx","docs_components_calendar.md":"BDO1Ekgw","docs_components_charts.md":"DUNfE0P_","docs_components_checkbox.md":"hbr0j66V","docs_components_circularprogressbar.md":"DLJJPz78","docs_components_combobox.md":"Y2e5TM29","docs_components_datepicker.md":"DyvSr0aM","docs_components_dialog.md":"uevpwsLT","docs_components_divider.md":"DBpGB8aK","docs_components_dropdown.md":"DE9Z-l1k","docs_components_errormessage.md":"CDld2Sg9","docs_components_fileuploader.md":"Cv_qAXZ2","docs_components_formcontrol.md":"Cvt-WJST","docs_components_itemlistrow.md":"BkOd_6mM","docs_components_keyboardshortcutsmodal.md":"CQpCw0i5","docs_components_legacy.md":"tGkba0ZB","docs_components_listview.md":"DdMrpUmg","docs_components_monthpicker.md":"DqUOipAd","docs_components_multiselect.md":"DYKufrEv","docs_components_password.md":"CgRJFSrs","docs_components_popover.md":"DmhywRRH","docs_components_progress.md":"Bs_hio7z","docs_components_rating.md":"C6mWcfP5","docs_components_select.md":"Qo8psXcd","docs_components_sidebar.md":"C2zfg9Ko","docs_components_slider.md":"BL9DvKHj","docs_components_switch.md":"27oxPTUr","docs_components_tabs.md":"Cg-SO4ia","docs_components_textarea.md":"Ds3EJgbW","docs_components_texteditor.md":"B4LCxMSs","docs_components_textinput.md":"BPgBS3Om","docs_components_timepicker.md":"B8AK39nA","docs_components_toast.md":"BMWK9lMr","docs_components_tooltip.md":"Bl50GtRn","docs_components_tree.md":"DqooW1Pb","docs_data-fetching_document-resource.md":"DXjR4m6w","docs_data-fetching_list-resource.md":"DDtlNqBH","docs_data-fetching_resource.md":"Co8cNx1P","docs_design-system_background-color.md":"DvZnnFO0","docs_design-system_border-color.md":"G3rFSBZG","docs_design-system_border-radius.md":"kbH27bpS","docs_design-system_drop-shadow.md":"BjaTHx-A","docs_design-system_text-color.md":"CNhN2ng7","docs_design-system_text.md":"D51r5pwR","docs_getting-started.md":"CxS2J9sr","docs_introduction.md":"zL5nf9EF","docs_migration.md":"njZvvwZ5","docs_molecules_editor.md":"CHx9GC8D","docs_other_directives.md":"BFqhndy_","docs_other_icons.md":"D84KlfIh","docs_other_utilities.md":"thPMyND2","index.md":"BJAv6mQZ"}
